tests/__init__.py
tests/test_ssh_tunnel.py
tests/docker/__init__.py
vantage6/node/__build__
vantage6/node/__init__.py
vantage6/node/_version.py
vantage6/node/context.py
vantage6/node/globals.py
vantage6/node/proxy_server.py
vantage6/node/socket.py
vantage6/node/cli/__init__.py
vantage6/node/cli/node.py
vantage6/node/docker/docker_base.py
vantage6/node/docker/docker_manager.py
vantage6/node/docker/exceptions.py
vantage6/node/docker/squid.py
vantage6/node/docker/ssh_tunnel.py
vantage6/node/docker/task_manager.py
vantage6/node/docker/vpn_manager.py
vantage6/node/util/__init__.py
vantage6/node/util/colorer.py
vantage6_node-4.13.6.dist-info/METADATA
vantage6_node-4.13.6.dist-info/WHEEL
vantage6_node-4.13.6.dist-info/entry_points.txt
vantage6_node-4.13.6.dist-info/top_level.txt
vantage6_node-4.13.6.dist-info/RECORD
