Metadata-Version: 2.4
Name: vantage6_node
Version: 4.13.6
Summary: vantage6 node
Home-page: https://github.com/vantage6/vantage6
Requires-Python: >=3.10
Requires-Dist: click==8.1.3
Requires-Dist: docker==7.1.0
Requires-Dist: gevent==25.4.2
Requires-Dist: jinja2==3.1.6
Requires-Dist: python-socketio==5.15.0
Requires-Dist: requests==2.32.4
Requires-Dist: psutil==5.9.0
Requires-Dist: nvidia-ml-py==12.535.133
Requires-Dist: vantage6==4.13.6
Requires-Dist: vantage6-client==4.13.6
Requires-Dist: vantage6-algorithm-tools==4.13.6
Provides-Extra: dev
Requires-Dist: coverage==6.4.4; extra == "dev"
Requires-Dist: python-coveralls==2.9.3; extra == "dev"
Requires-Dist: SQLAlchemy==1.4.46; extra == "dev"
Requires-Dist: schema==0.7.5; extra == "dev"
Requires-Dist: appdirs==1.4.4; extra == "dev"
Requires-Dist: flask==3.1.1; extra == "dev"
Requires-Dist: black; extra == "dev"
Requires-Dist: pre-commit; extra == "dev"
Dynamic: description
Dynamic: description-content-type
Dynamic: home-page
Dynamic: provides-extra
Dynamic: requires-dist
Dynamic: requires-python
Dynamic: summary
